README.md
setup.py
src/vdk/api/lineage/model/logger/lineage_logger.py
src/vdk/api/lineage/model/sql/model.py
src/vdk_lineage_model.egg-info/PKG-INFO
src/vdk_lineage_model.egg-info/SOURCES.txt
src/vdk_lineage_model.egg-info/dependency_links.txt
src/vdk_lineage_model.egg-info/top_level.txt
tests/test_sql_model.py