Metadata-Version: 2.1
Name: vdk-lineage-model
Version: 0.0.824443273
Summary: VDK Lineage Model plugin defines common lineage model and classes used for managing lineageinformation in other VDK plugins.
Home-page: https://github.com/vmware/versatile-data-kit
Classifier: Development Status :: 2 - Pre-Alpha
Classifier: License :: OSI Approved :: Apache Software License
Classifier: Programming Language :: Python :: 3.7
Classifier: Programming Language :: Python :: 3.8
Classifier: Programming Language :: Python :: 3.9
Classifier: Programming Language :: Python :: 3.10
Classifier: Programming Language :: Python :: 3.11
